stemflow/__init__.py
stemflow/model_selection.py
stemflow/version.py
stemflow/gridding/QTree.py
stemflow/gridding/Q_blocks.py
stemflow/gridding/QuadGrid.py
stemflow/gridding/Sphere_QTree.py
stemflow/gridding/__init__.py
stemflow/lazyloading/__init__.py
stemflow/lazyloading/lazyloading.py
stemflow/lazyloading/open_db_connection.py
stemflow/model/AdaSTEM.py
stemflow/model/Hurdle.py
stemflow/model/STEM.py
stemflow/model/SphereAdaSTEM.py
stemflow/model/__init__.py
stemflow/model/dummy_model.py
stemflow/model/special_hurdle.py
stemflow/model/static_func_AdaSTEM.py
stemflow/utils/__init__.py
stemflow/utils/generate_random.py
stemflow/utils/generate_soft_colors.py
stemflow/utils/lazyloading.py
stemflow/utils/plot_gif.py
stemflow/utils/quadtree.py
stemflow/utils/sphere_quadtree.py
stemflow/utils/validation.py
stemflow/utils/wrapper.py
stemflow/utils/jitterrotation/__init__.py
stemflow/utils/jitterrotation/jitterrotator.py
stemflow/utils/sphere/Icosahedron.py
stemflow/utils/sphere/__init__.py
stemflow/utils/sphere/coordinate_transform.py
stemflow/utils/sphere/discriminant_formula.py
stemflow/utils/sphere/distance.py
tests/__init__.py
tests/make_models.py
tests/set_up_data.py
tests/test_all.py
tests/test_duckdb_input.py
tests/test_joblib_temp_folder.py
tests/test_lazy_loading_dict.py
tests/test_makegif.py
tests/test_model.py
tests/test_model_custom_base_model_method.py
tests/test_model_ensemble_bootstrap.py
tests/test_model_lazy_loading.py
tests/test_model_prediction_logit_aggregation.py
tests/test_model_selection.py
tests/test_parquet_input.py
tests/test_random_state_reproducibility.py
tests/test_save_load_del.py
stemflow-1.1.5.dist-info/LICENSE
stemflow-1.1.5.dist-info/METADATA
stemflow-1.1.5.dist-info/WHEEL
stemflow-1.1.5.dist-info/top_level.txt
stemflow-1.1.5.dist-info/RECORD
