Metadata-Version: 2.1
Name: stemflow
Version: 1.1.5
Summary: A package for Adaptive Spatio-Temporal Exploratory Model (AdaSTEM) in python
Home-page: https://github.com/chenyangkang/stemflow
Author: Yangkang Chen
Author-email: chenyangkang24@outlook.com
Keywords: python,spatial-temporal model,ebird,citizen science,spatial temporal exploratory model,STEM,AdaSTEM,abundance,phenology
Platform: any
Classifier: Development Status :: 5 - Production/Stable
Classifier: Programming Language :: Python :: 3
Classifier: Programming Language :: Python :: 3.9
Classifier: Programming Language :: Python :: 3.10
Classifier: Programming Language :: Python :: 3.11
Classifier: Programming Language :: Python :: 3.12
Classifier: Operating System :: Unix
Classifier: Operating System :: MacOS :: MacOS X
Classifier: Operating System :: Microsoft :: Windows
Requires-Python: >=3.9.0
License-File: LICENSE
Requires-Dist: joblib>=1.3.0
Requires-Dist: matplotlib>=3.7.1
Requires-Dist: numpy<2,>=1.24.3
Requires-Dist: pandas>=2.2.0
Requires-Dist: plotly>=5.9.0
Requires-Dist: scikit_learn<1.6,>=1.2.2
Requires-Dist: scipy>=1.10.1
Requires-Dist: setuptools>=68.2.0
Requires-Dist: tqdm>=4.65.0
Requires-Dist: duckdb>=1.1.3
Requires-Dist: pyarrow>=17.0.0
